fishlib/__init__.py
fishlib/matcher.py
fishlib/parser.py
fishlib/standards.py
fishlib/data/species_aliases.json
fishlib/data/standard_codes.json
fishlib/reference/__init__.py
fishlib/species/__init__.py
fishlib-0.1.0.dist-info/licenses/LICENSE
tests/__init__.py
tests/test_fishlib.py
fishlib-0.1.0.dist-info/METADATA
fishlib-0.1.0.dist-info/WHEEL
fishlib-0.1.0.dist-info/top_level.txt
fishlib-0.1.0.dist-info/RECORD
